Workbook

Sheet Regional_Lookup
A1: Region | B1: Regional_Manager | C1: Target_Profit_Margin
A2: Central | B2: David Johnson | C2: 0.14
A3: East | B3: Sarah Miller | C3: 0.16
A4: South | B4: Maria Santos | C4: 0.15
A5: West | B5: James Chen | C5: 0.18

Sheet Sample - Superstore
A1: Row ID | B1: Order ID | C1: Order Date | D1: Ship Date | E1: Ship Mode | F1: Customer ID | G1: Customer Name | H1: Segment | I1: Country | J1: City | K1: State | L1: Postal Code | M1: Region | N1: Product ID | O1: Category | P1: Sub-Category | Q1: Product Name | R1: Sales | S1: Quantity | T1: Discount | U1: Profit | V1: Regional_Manager | W1: Target_Profit_Margin | X1: Profit_Margin | Y1: Above_Target | Z1: Days_to_Ship | AA1: Ship_Performance
A2: 1 | B2: CA-2016-152156 | C2: 42682 | D2: 42685 | E2: Second Class | F2: CG-12520 | G2: Claire Gute | H2: Consumer | I2: United States | J2: Henderson | K2: Kentucky | L2: 42420 | M2: South | N2: FUR-BO-10001798 | O2: Furniture | P2: Bookcases | Q2: Bush Somerset Collection Bookcase | R2: 261.96 | S2: 2 | T2: 0 | U2: 41.9136 | V2: =INDEX(Regional_Lookup!$B$2:$B$5,MATCH('Sample - Superstore'!M2,Regional_Lookup!$A$2:$A$5,0)) -> Maria Santos | W2: =INDEX(Regional_Lookup!$C$2:$C$5, MATCH('Sample - Superstore'!M2,Regional_Lookup!$A$2:$A$5, 0)) -> 0.15 | X2: =U2/R2 -> 0.16 | Y2: =IF(X2>=W2, "Yes", "No") -> Yes | Z2: =D2-C2 -> 3 | AA2: {=_xlfn.IFS(Z2<=2,"Fast",Z2>5, "Slow", AND(Z2>=3,Z2<=5),"Standard")} -> Standard
A3: 2 | B3: CA-2016-152156 | C3: 42682 | D3: 42685 | E3: Second Class | F3: CG-12520 | G3: Claire Gute | H3: Consumer | I3: United States | J3: Henderson | K3: Kentucky | L3: 42420 | M3: South | N3: FUR-CH-10000454 | O3: Furniture | P3: Chairs | Q3: Hon Deluxe Fabric Upholstered Stacking Chairs, Rounded Back | R3: 731.94 | S3: 3 | T3: 0 | U3: 219.582 | V3: =INDEX(Regional_Lookup!$B$2:$B$5,MATCH('Sample - Superstore'!M3,Regional_Lookup!$A$2:$A$5,0)) -> Maria Santos | W3: =INDEX(Regional_Lookup!$C$2:$C$5, MATCH('Sample - Superstore'!M3,Regional_Lookup!$A$2:$A$5, 0)) -> 0.15 | X3: =U3/R3 -> 0.3 | Y3: =IF(X3>=W3, "Yes", "No") -> Yes | Z3: =D3-C3 -> 3 | AA3: {=_xlfn.IFS(Z3<=2,"Fast",Z3>5, "Slow", AND(Z3>=3,Z3<=5),"Standard")} -> Standard
A4: 3 | B4: CA-2016-138688 | C4: 42533 | D4: 42537 | E4: Second Class | F4: DV-13045 | G4: Darrin Van Huff | H4: Corporate | I4: United States | J4: Los Angeles | K4: California | L4: 90036 | M4: West | N4: OFF-LA-10000240 | O4: Office Supplies | P4: Labels | Q4: Self-Adhesive Address Labels for Typewriters by Universal | R4: 14.62 | S4: 2 | T4: 0 | U4: 6.8714 | V4: =INDEX(Regional_Lookup!$B$2:$B$5,MATCH('Sample - Superstore'!M4,Regional_Lookup!$A$2:$A$5,0)) -> James Chen | W4: =INDEX(Regional_Lookup!$C$2:$C$5, MATCH('Sample - Superstore'!M4,Regional_Lookup!$A$2:$A$5, 0)) -> 0.18 | X4: =U4/R4 -> 0.47 | Y4: =IF(X4>=W4, "Yes", "No") -> Yes | Z4: =D4-C4 -> 4 | AA4: {=_xlfn.IFS(Z4<=2,"Fast",Z4>5, "Slow", AND(Z4>=3,Z4<=5),"Standard")} -> Standard
A5: 4 | B5: US-2015-108966 | C5: 42288 | D5: 42295 | E5: Standard Class | F5: SO-20335 | G5: Sean O'Donnell | H5: Consumer | I5: United States | J5: Fort Lauderdale | K5: Florida | L5: 33311 | M5: South | N5: FUR-TA-10000577 | O5: Furniture | P5: Tables | Q5: Bretford CR4500 Series Slim Rectangular Table | R5: 957.5775 | S5: 5 | T5: 0.45 | U5: -383.031 | V5: =INDEX(Regional_Lookup!$B$2:$B$5,MATCH('Sample - Superstore'!M5,Regional_Lookup!$A$2:$A$5,0)) -> Maria Santos | W5: =INDEX(Regional_Lookup!$C$2:$C$5, MATCH('Sample - Superstore'!M5,Regional_Lookup!$A$2:$A$5, 0)) -> 0.15 | X5: =U5/R5 -> -0.4 | Y5: =IF(X5>=W5, "Yes", "No") -> No | Z5: =D5-C5 -> 7 | AA5: {=_xlfn.IFS(Z5<=2,"Fast",Z5>5, "Slow", AND(Z5>=3,Z5<=5),"Standard")} -> Slow
A6: 5 | B6: US-2015-108966 | C6: 42288 | D6: 42295 | E6: Standard Class | F6: SO-20335 | G6: Sean O'Donnell | H6: Consumer | I6: United States | J6: Fort Lauderdale | K6: Florida | L6: 33311 | M6: South | N6: OFF-ST-10000760 | O6: Office Supplies | P6: Storage | Q6: Eldon Fold 'N Roll Cart System | R6: 22.368 | S6: 2 | T6: 0.2 | U6: 2.5164 | V6: =INDEX(Regional_Lookup!$B$2:$B$5,MATCH('Sample - Superstore'!M6,Regional_Lookup!$A$2:$A$5,0)) -> Maria Santos | W6: =INDEX(Regional_Lookup!$C$2:$C$5, MATCH('Sample - Superstore'!M6,Regional_Lookup!$A$2:$A$5, 0)) -> 0.15 | X6: =U6/R6 -> 0.1125 | Y6: =IF(X6>=W6, "Yes", "No") -> No | Z6: =D6-C6 -> 7 | AA6: {=_xlfn.IFS(Z6<=2,"Fast",Z6>5, "Slow", AND(Z6>=3,Z6<=5),"Standard")} -> Slow
A7: 6 | B7: CA-2014-115812 | C7: 41799 | D7: 41804 | E7: Standard Class | F7: BH-11710 | G7: Brosina Hoffman | H7: Consumer | I7: United States | J7: Los Angeles | K7: California | L7: 90032 | M7: West | N7: FUR-FU-10001487 | O7: Furniture | P7: Furnishings | Q7: Eldon Expressions Wood and Plastic Desk Accessories, Cherry Wood | R7: 48.86 | S7: 7 | T7: 0 | U7: 14.1694 | V7: =INDEX(Regional_Lookup!$B$2:$B$5,MATCH('Sample - Superstore'!M7,Regional_Lookup!$A$2:$A$5,0)) -> James Chen | W7: =INDEX(Regional_Lookup!$C$2:$C$5, MATCH('Sample - Superstore'!M7,Regional_Lookup!$A$2:$A$5, 0)) -> 0.18 | X7: =U7/R7 -> 0.29 | Y7: =IF(X7>=W7, "Yes", "No") -> Yes | Z7: =D7-C7 -> 5 | AA7: {=_xlfn.IFS(Z7<=2,"Fast",Z7>5, "Slow", AND(Z7>=3,Z7<=5),"Standard")} -> Standard
A8: 7 | B8: CA-2014-115812 | C8: 41799 | D8: 41804 | E8: Standard Class | F8: BH-11710 | G8: Brosina Hoffman | H8: Consumer | I8: United States | J8: Los Angeles | K8: California | L8: 90032 | M8: West | N8: OFF-AR-10002833 | O8: Office Supplies | P8: Art | Q8: Newell 322 | R8: 7.28 | S8: 4 | T8: 0 | U8: 1.9656 | V8: =INDEX(Regional_Lookup!$B$2:$B$5,MATCH('Sample - Superstore'!M8,Regional_Lookup!$A$2:$A$5,0)) -> James Chen | W8: =INDEX(Regional_Lookup!$C$2:$C$5, MATCH('Sample - Superstore'!M8,Regional_Lookup!$A$2:$A$5, 0)) -> 0.18 | X8: =U8/R8 -> 0.27 | Y8: =IF(X8>=W8, "Yes", "No") -> Yes | Z8: =D8-C8 -> 5 | AA8: {=_xlfn.IFS(Z8<=2,"Fast",Z8>5, "Slow", AND(Z8>=3,Z8<=5),"Standard")} -> Standard
A9: 8 | B9: CA-2014-115812 | C9: 41799 | D9: 41804 | E9: Standard Class | F9: BH-11710 | G9: Brosina Hoffman | H9: Consumer | I9: United States | J9: Los Angeles | K9: California | L9: 90032 | M9: West | N9: TEC-PH-10002275 | O9: Technology | P9: Phones | Q9: Mitel 5320 IP Phone VoIP phone | R9: 907.152 | S9: 6 | T9: 0.2 | U9: 90.7152 | V9: =INDEX(Regional_Lookup!$B$2:$B$5,MATCH('Sample - Superstore'!M9,Regional_Lookup!$A$2:$A$5,0)) -> James Chen | W9: =INDEX(Regional_Lookup!$C$2:$C$5, MATCH('Sample - Superstore'!M9,Regional_Lookup!$A$2:$A$5, 0)) -> 0.18 | X9: =U9/R9 -> 0.1 | Y9: =IF(X9>=W9, "Yes", "No") -> No | Z9: =D9-C9 -> 5 | AA9: {=_xlfn.IFS(Z9<=2,"Fast",Z9>5, "Slow", AND(Z9>=3,Z9<=5),"Standard")} -> Standard
A10: 9 | B10: CA-2014-115812 | C10: 41799 | D10: 41804 | E10: Standard Class | F10: BH-11710 | G10: Brosina Hoffman | H10: Consumer | I10: United States | J10: Los Angeles | K10: California | L10: 90032 | M10: West | N10: OFF-BI-10003910 | O10: Office Supplies | P10: Binders | Q10: DXL Angle-View Binders with Locking Rings by Samsill | R10: 18.504 | S10: 3 | T10: 0.2 | U10: 5.7825 | V10: =INDEX(Regional_Lookup!$B$2:$B$5,MATCH('Sample - Superstore'!M10,Regional_Lookup!$A$2:$A$5,0)) -> James Chen | W10: =INDEX(Regional_Lookup!$C$2:$C$5, MATCH('Sample - Superstore'!M10,Regional_Lookup!$A$2:$A$5, 0)) -> 0.18 | X10: =U10/R10 -> 0.3125 | Y10: =IF(X10>=W10, "Yes", "No") -> Yes | Z10: =D10-C10 -> 5 | AA10: {=_xlfn.IFS(Z10<=2,"Fast",Z10>5, "Slow", AND(Z10>=3,Z10<=5),"Standard")} -> Standard
A11: 10 | B11: CA-2014-115812 | C11: 41799 | D11: 41804 | E11: Standard Class | F11: BH-11710 | G11: Brosina Hoffman | H11: Consumer | I11: United States | J11: Los Angeles | K11: California | L11: 90032 | M11: West | N11: OFF-AP-10002892 | O11: Office Supplies | P11: Appliances | Q11: Belkin F5C206VTEL 6 Outlet Surge | R11: 114.9 | S11: 5 | T11: 0 | U11: 34.47 | V11: =INDEX(Regional_Lookup!$B$2:$B$5,MATCH('Sample - Superstore'!M11,Regional_Lookup!$A$2:$A$5,0)) -> James Chen | W11: =INDEX(Regional_Lookup!$C$2:$C$5, MATCH('Sample - Superstore'!M11,Regional_Lookup!$A$2:$A$5, 0)) -> 0.18 | X11: =U11/R11 -> 0.3 | Y11: =IF(X11>=W11, "Yes", "No") -> Yes | Z11: =D11-C11 -> 5 | AA11: {=_xlfn.IFS(Z11<=2,"Fast",Z11>5, "Slow", AND(Z11>=3,Z11<=5),"Standard")} -> Standard
A12: 11 | B12: CA-2014-115812 | C12: 41799 | D12: 41804 | E12: Standard Class | F12: BH-11710 | G12: Brosina Hoffman | H12: Consumer | I12: United States | J12: Los Angeles | K12: California | L12: 90032 | M12: West | N12: FUR-TA-10001539 | O12: Furniture | P12: Tables | Q12: Chromcraft Rectangular Conference Tables | R12: 1706.184 | S12: 9 | T12: 0.2 | U12: 85.3092 | V12: =INDEX(Regional_Lookup!$B$2:$B$5,MATCH('Sample - Superstore'!M12,Regional_Lookup!$A$2:$A$5,0)) -> James Chen | W12: =INDEX(Regional_Lookup!$C$2:$C$5, MATCH('Sample - Superstore'!M12,Regional_Lookup!$A$2:$A$5, 0)) -> 0.18 | X12: =U12/R12 -> 0.05 | Y12: =IF(X12>=W12, "Yes", "No") -> No | Z12: =D12-C12 -> 5 | AA12: {=_xlfn.IFS(Z12<=2,"Fast",Z12>5, "Slow", AND(Z12>=3,Z12<=5),"Standard")} -> Standard
A13: 12 | B13: CA-2014-115812 | C13: 41799 | D13: 41804 | E13: Standard Class | F13: BH-11710 | G13: Brosina Hoffman | H13: Consumer | I13: United States | J13: Los Angeles | K13: California | L13: 90032 | M13: West | N13: TEC-PH-10002033 | O13: Technology | P13: Phones | Q13: Konftel 250 Conference†phone†- Charcoal black | R13: 911.424 | S13: 4 | T13: 0.2 | U13: 68.3568 | V13: =INDEX(Regional_Lookup!$B$2:$B$5,MATCH('Sample - Superstore'!M13,Regional_Lookup!$A$2:$A$5,0)) -> James Chen | W13: =INDEX(Regional_Lookup!$C$2:$C$5, MATCH('Sample - Superstore'!M13,Regional_Lookup!$A$2:$A$5, 0)) -> 0.18 | X13: =U13/R13 -> 0.075 | Y13: =IF(X13>=W13, "Yes", "No") -> No | Z13: =D13-C13 -> 5 | AA13: {=_xlfn.IFS(Z13<=2,"Fast",Z13>5, "Slow", AND(Z13>=3,Z13<=5),"Standard")} -> Standard
... A9995: 9994 | B9995: CA-2017-119914 | C9995: 42859 | D9995: 42864 | E9995: Second Class | F9995: CC-12220 | G9995: Chris Cortes | H9995: Consumer | I9995: United States | J9995: Westminster | K9995: California | L9995: 92683 | M9995: West | N9995: OFF-AP-10002684 | O9995: Office Supplies | P9995: Appliances | Q9995: Acco 7-Outlet Masterpiece Power Center, Wihtout Fax/Phone Line Protection | R9995: 243.16 | S9995: 2 | T9995: 0 | U9995: 72.948 | V9995: =INDEX(Regional_Lookup!$B$2:$B$5,MATCH('Sample - Superstore'!M9995,Regional_Lookup!$A$2:$A$5,0)) -> James Chen | W9995: =INDEX(Regional_Lookup!$C$2:$C$5, MATCH('Sample - Superstore'!M9995,Regional_Lookup!$A$2:$A$5, 0)) -> 0.18 | X9995: =U9995/R9995 -> 0.3 | Y9995: =IF(X9995>=W9995, "Yes", "No") -> Yes | Z9995: =D9995-C9995 -> 5 | AA9995: {=_xlfn.IFS(Z9995<=2,"Fast",Z9995>5, "Slow", AND(Z9995>=3,Z9995<=5),"Standard")} -> Standard
